dc43_contracts_app/__init__.py
dc43_contracts_app/_odcs.py
dc43_contracts_app/_versioning.py
dc43_contracts_app/config.py
dc43_contracts_app/docs_chat.py
dc43_contracts_app/docs_chat_index.py
dc43_contracts_app/hints.py
dc43_contracts_app/server.py
dc43_contracts_app/services.py
dc43_contracts_app/config/default.toml
dc43_contracts_app/setup_bundle/__init__.py
dc43_contracts_app/setup_bundle/pipeline_stub.py
dc43_contracts_app/static/chart.umd.js
dc43_contracts_app/static/flow-read.png
dc43_contracts_app/static/flow-write.png
dc43_contracts_app/static/flow.png
dc43_contracts_app/static/presentation.html
dc43_contracts_app/static/setup-wizard-template.json
dc43_contracts_app/static/setup.js
dc43_contracts_app/templates/base.html
dc43_contracts_app/templates/contract_detail.html
dc43_contracts_app/templates/contract_versions.html
dc43_contracts_app/templates/contracts.html
dc43_contracts_app/templates/data_product_detail.html
dc43_contracts_app/templates/data_products.html
dc43_contracts_app/templates/dataset_detail.html
dc43_contracts_app/templates/dataset_versions.html
dc43_contracts_app/templates/datasets.html
dc43_contracts_app/templates/docs_chat.html
dc43_contracts_app/templates/index.html
dc43_contracts_app/templates/integration_helper.html
dc43_contracts_app/templates/new_contract.html
dc43_contracts_app/templates/new_data_product.html
dc43_contracts_app/templates/setup.html
dc43_contracts_app/templates/includes/metrics_chart_script.html
dc43_contracts_app/templates/includes/metrics_summary.html
dc43_contracts_app-0.32.0.0.dist-info/METADATA
dc43_contracts_app-0.32.0.0.dist-info/WHEEL
dc43_contracts_app-0.32.0.0.dist-info/entry_points.txt
dc43_contracts_app-0.32.0.0.dist-info/top_level.txt
dc43_contracts_app-0.32.0.0.dist-info/RECORD
