Metadata-Version: 2.4
Name: dc43-contracts-app
Version: 0.32.0.0
Summary: FastAPI portal for browsing and editing DC43 contracts and datasets
Author: Andy Petrella
Classifier: Programming Language :: Python :: 3
Classifier: License :: OSI Approved :: MIT License
Classifier: Operating System :: OS Independent
Requires-Python: >=3.11
Requires-Dist: dc43-service-clients>=0.32.0.0
Requires-Dist: dc43-service-backends>=0.32.0.0
Requires-Dist: fastapi>=0.118.0
Requires-Dist: jinja2>=3.1.0
Requires-Dist: python-multipart>=0.0.5
Requires-Dist: httpx>=0.24
Requires-Dist: tomlkit>=0.12
Provides-Extra: spark
Requires-Dist: dc43-integrations[lineage,spark,telemetry]>=0.32.0.0; extra == "spark"
Provides-Extra: test
Requires-Dist: dc43-service-clients[lineage,test]>=0.32.0.0; extra == "test"
Requires-Dist: dc43-service-backends[test]>=0.32.0.0; extra == "test"
Requires-Dist: dc43-integrations[lineage,spark,telemetry,test]>=0.32.0.0; extra == "test"
Requires-Dist: httpx>=0.24; extra == "test"
Provides-Extra: docs-chat
Requires-Dist: gradio>=4.33.0; extra == "docs-chat"
Requires-Dist: langchain>=0.1.17; extra == "docs-chat"
Requires-Dist: langchain-community>=0.0.37; extra == "docs-chat"
Requires-Dist: langchain-openai>=0.1.3; extra == "docs-chat"
Requires-Dist: langchain-text-splitters>=0.0.1; extra == "docs-chat"
Requires-Dist: chardet>=5.0; extra == "docs-chat"
Requires-Dist: faiss-cpu>=1.7.4; extra == "docs-chat"
Requires-Dist: langchain-huggingface>=0.1.2; extra == "docs-chat"
Requires-Dist: sentence-transformers>=2.2; extra == "docs-chat"
